Metadata-Version: 2.1
Name: phigaro
Version: 2.4.0
Summary: Phigaro is a scalable command-line tool for predicting phages and prophages.
Home-page: https://github.com/bobeobibo/phigaro
Author: E.Starikova, N.Pryanichnikov, P.Tikhonova
Author-email: hed.robin@gmail.com
License: MIT
Platform: UNKNOWN
License-File: LICENSE.md
Requires-Dist: numpy
Requires-Dist: six (>=1.7.0)
Requires-Dist: pandas (>=0.23.4)
Requires-Dist: sh
Requires-Dist: singleton
Requires-Dist: PyYAML (>=5.1)
Requires-Dist: future
Requires-Dist: argparse
Requires-Dist: plotly
Requires-Dist: bs4
Requires-Dist: beautifulsoup4 (>=4.4.0)
Requires-Dist: lxml
Requires-Dist: biopython
